exotools/__init__.py
exotools/constants.py
exotools/py.typed
exotools/datasets/__init__.py
exotools/datasets/_exoplanet_dataset_reducer.py
exotools/datasets/base_dataset.py
exotools/datasets/candidate_exoplanets.py
exotools/datasets/gaia_parameters.py
exotools/datasets/known_exoplanets.py
exotools/datasets/lightcurves.py
exotools/datasets/tic_catalog.py
exotools/datasets/tic_observations.py
exotools/db/__init__.py
exotools/db/base_db.py
exotools/db/candidate_db.py
exotools/db/exo_db.py
exotools/db/gaia_db.py
exotools/db/lightcurve_db.py
exotools/db/lightcurve_plus.py
exotools/db/starsystem_db.py
exotools/db/tess_meta_db.py
exotools/db/tic_db.py
exotools/db/star_system/__init__.py
exotools/db/star_system/planet.py
exotools/db/star_system/star.py
exotools/db/star_system/star_system.py
exotools/db/star_system/uncertain_data.py
exotools/downloaders/__init__.py
exotools/downloaders/_utils.py
exotools/downloaders/candidate_exoplanets_downloader.py
exotools/downloaders/dataset_downloader.py
exotools/downloaders/exoplanets_downloader.py
exotools/downloaders/gaia_downloader.py
exotools/downloaders/lightcurve_downloader.py
exotools/downloaders/tap_service.py
exotools/downloaders/tess_catalog_downloader.py
exotools/downloaders/tess_observations_downloader.py
exotools/io/__init__.py
exotools/io/base_storage.py
exotools/io/fs_storage.py
exotools/io/hdf5_storage.py
exotools/io/memory_storage.py
exotools/utils/__init__.py
exotools/utils/array_utils.py
exotools/utils/download.py
exotools/utils/masked_operations.py
exotools/utils/observations_fix.py
exotools/utils/qtable_utils.py
exotools/utils/unit_mapper.py
exotools-0.0.4.dist-info/licenses/LICENSE
exotools-0.0.4.dist-info/METADATA
exotools-0.0.4.dist-info/WHEEL
exotools-0.0.4.dist-info/top_level.txt
exotools-0.0.4.dist-info/RECORD
