Metadata-Version: 2.4
Name: exotools
Version: 0.0.4
Summary: Tools for working with exoplanet data
Author-email: Christian Cardin <astro.sech@gmail.com>
License: MIT License
Project-URL: Homepage, https://github.com/sechlol/exotools
Project-URL: Bug Tracker, https://github.com/sechlol/exotools/issues
Project-URL: Documentation, https://github.com/sechlol/exotools
Classifier: Programming Language :: Python :: 3
Classifier: Programming Language :: Python :: 3.10
Classifier: Programming Language :: Python :: 3.11
Classifier: Programming Language :: Python :: 3.12
Classifier: Programming Language :: Python :: 3.13
Classifier: License :: OSI Approved :: MIT License
Classifier: Operating System :: OS Independent
Classifier: Development Status :: 4 - Beta
Classifier: Intended Audience :: Science/Research
Classifier: Topic :: Scientific/Engineering :: Astronomy
Requires-Python: >=3.10
License-File: LICENSE
Requires-Dist: numpy
Requires-Dist: pandas[performance]
Requires-Dist: pyarrow==18.1.0
Requires-Dist: tables
Requires-Dist: tabulate
Requires-Dist: h5py
Requires-Dist: pydantic
Requires-Dist: oktopus
Requires-Dist: lightkurve
Requires-Dist: astropy
Requires-Dist: astroquery
Requires-Dist: casjobs
Requires-Dist: tqdm
Requires-Dist: pyvo
Requires-Dist: tomli
Provides-Extra: dev
Requires-Dist: pytest; extra == "dev"
Requires-Dist: pytest-cov; extra == "dev"
Requires-Dist: python-dotenv; extra == "dev"
Requires-Dist: ruff; extra == "dev"
Dynamic: license-file
